{
  "indexes": [
    {
      "collectionGroup": "posts",
      "queryScope": "COLLECTION",
      "fields": [
        { "fieldPath": "authorId", "order": "ASCENDING" },
        { "fieldPath": "postScore", "order": "DESCENDING" }
      ]
    },
    {
      "collectionGroup": "posts",
      "queryScope": "COLLECTION",
      "fields": [
        { "fieldPath": "authorId", "order": "ASCENDING" },
        { "fieldPath": "createdAt", "order": "DESCENDING" }
      ]
    },
    {
      "collectionGroup": "posts",
      "queryScope": "COLLECTION",
      "fields": [
        { "fieldPath": "authorId", "order": "ASCENDING" },
        { "fieldPath": "createdAt", "order": "ASCENDING" }
      ]
    },
    {
      "collectionGroup": "posts",
      "queryScope": "COLLECTION",
      "fields": [
        { "fieldPath": "postScore", "order": "DESCENDING" },
        { "fieldPath": "createdAt", "order": "DESCENDING" }
      ]
    },
    {
      "collectionGroup": "posts",
      "queryScope": "COLLECTION",
      "fields": [
        { "fieldPath": "segmentKey", "order": "ASCENDING" },
        { "fieldPath": "postScore", "order": "DESCENDING" }
      ]
    },
    {
      "collectionGroup": "posts",
      "queryScope": "COLLECTION",
      "fields": [
        { "fieldPath": "metadata.country", "order": "ASCENDING" },
        { "fieldPath": "postScore", "order": "DESCENDING" }
      ]
    },
    {
      "collectionGroup": "posts",
      "queryScope": "COLLECTION",
      "fields": [
        { "fieldPath": "metadata.city", "order": "ASCENDING" },
        { "fieldPath": "postScore", "order": "DESCENDING" }
      ]
    },
    {
      "collectionGroup": "posts",
      "queryScope": "COLLECTION",
      "fields": [
        { "fieldPath": "metadata.gender", "order": "ASCENDING" },
        { "fieldPath": "postScore", "order": "DESCENDING" }
      ]
    },
    {
      "collectionGroup": "posts",
      "queryScope": "COLLECTION",
      "fields": [
        { "fieldPath": "metadata.age", "order": "ASCENDING" },
        { "fieldPath": "postScore", "order": "DESCENDING" }
      ]
    },
    {
      "collectionGroup": "posts",
      "queryScope": "COLLECTION",
      "fields": [
        { "fieldPath": "metadata.profession", "order": "ASCENDING" },
        { "fieldPath": "postScore", "order": "DESCENDING" }
      ]
    },
    {
      "collectionGroup": "posts",
      "queryScope": "COLLECTION",
      "fields": [
        { "fieldPath": "metadata.maritalStatus", "order": "ASCENDING" },
        { "fieldPath": "postScore", "order": "DESCENDING" }
      ]
    },
    {
      "collectionGroup": "posts",
      "queryScope": "COLLECTION",
      "fields": [
        { "fieldPath": "metadata.country", "order": "ASCENDING" },
        { "fieldPath": "metadata.city", "order": "ASCENDING" },
        { "fieldPath": "postScore", "order": "DESCENDING" }
      ]
    },
    {
      "collectionGroup": "interactions",
      "queryScope": "COLLECTION",
      "fields": [
        { "fieldPath": "postId", "order": "ASCENDING" },
        { "fieldPath": "createdAt", "order": "DESCENDING" }
      ]
    },
    {
      "collectionGroup": "interactions",
      "queryScope": "COLLECTION",
      "fields": [
        { "fieldPath": "postId", "order": "ASCENDING" },
        { "fieldPath": "type", "order": "ASCENDING" },
        { "fieldPath": "createdAt", "order": "DESCENDING" }
      ]
    },
    {
      "collectionGroup": "actorEngagements",
      "queryScope": "COLLECTION",
      "fields": [
        { "fieldPath": "actorId", "order": "ASCENDING" },
        { "fieldPath": "saved", "order": "ASCENDING" }
      ]
    },
    {
      "collectionGroup": "follows",
      "queryScope": "COLLECTION",
      "fields": [
        { "fieldPath": "followerId", "order": "ASCENDING" },
        { "fieldPath": "createdAt", "order": "DESCENDING" }
      ]
    },
    {
      "collectionGroup": "follows",
      "queryScope": "COLLECTION",
      "fields": [
        { "fieldPath": "targetUserId", "order": "ASCENDING" },
        { "fieldPath": "createdAt", "order": "DESCENDING" }
      ]
    },
    {
      "collectionGroup": "posts",
      "queryScope": "COLLECTION",
      "fields": [
        { "fieldPath": "hashtags", "arrayConfig": "CONTAINS" },
        { "fieldPath": "createdAt", "order": "DESCENDING" }
      ]
    },
    {
      "collectionGroup": "stories",
      "queryScope": "COLLECTION",
      "fields": [
        { "fieldPath": "userId", "order": "ASCENDING" },
        { "fieldPath": "createdAt", "order": "ASCENDING" }
      ]
    },
    {
      "collectionGroup": "stories",
      "queryScope": "COLLECTION",
      "fields": [
        { "fieldPath": "expiresAt", "order": "ASCENDING" },
        { "fieldPath": "createdAt", "order": "DESCENDING" }
      ]
    }
  ],
  "fieldOverrides": [
    {
      "collectionGroup": "items",
      "fieldPath": "postId",
      "ttl": false,
      "indexes": [
        {
          "order": "ASCENDING",
          "queryScope": "COLLECTION"
        },
        {
          "order": "ASCENDING",
          "queryScope": "COLLECTION_GROUP"
        }
      ]
    }
  ]
}
